tjhome/__init__.py
tjhome/_modidx.py
tjhome/air_quality.py
tjhome/repository.py
tjhome-0.1.0.dist-info/WHEEL
tjhome-0.1.0.dist-info/METADATA
tjhome-0.1.0.dist-info/RECORD
