Metadata-Version: 2.1
Name: tjhome
Version: 0.1.0
Summary: TJ's Smart Home Utilities
Home-page: https://tjpalanca.com/tjhome
License: AGPL-3.0
Author: TJ Palanca
Author-email: mail@tjpalanca.com
Requires-Python: >=3.10,<4.0
Classifier: License :: OSI Approved :: GNU Affero General Public License v3
Classifier: Programming Language :: Python :: 3
Classifier: Programming Language :: Python :: 3.10
Classifier: Programming Language :: Python :: 3.11
Requires-Dist: dagit (>=0.15.6,<0.16.0)
Requires-Dist: dagster (>=0.15.6,<0.16.0)
Requires-Dist: pydantic (>=1.10.2,<2.0.0)
Requires-Dist: requests (>=2.28.1,<3.0.0)
Requires-Dist: tuya-iot-py-sdk (>=0.6.6,<0.7.0)
Requires-Dist: types-requests (>=2.28.1,<3.0.0)
Project-URL: Documentation, https://tjpalanca.com/tjhome
Project-URL: Repository, https://github.com/tjpalanca/tjhome.git
